helios/__init__.py
helios/alerts_api.py
helios/cameras_api.py
helios/collections_api.py
helios/observations_api.py
helios/core/__init__.py
helios/core/config.py
helios/core/mixins.py
helios/core/request_manager.py
helios/core/session.py
helios/core/structure.py
helios/utilities/__init__.py
helios/utilities/data_utils.py
helios/utilities/json_utils.py
helios/utilities/logging_utils.py
helios/utilities/parsing_utils.py
helios_sdk-3.0.1.dist-info/METADATA
helios_sdk-3.0.1.dist-info/RECORD
helios_sdk-3.0.1.dist-info/WHEEL
helios_sdk-3.0.1.dist-info/top_level.txt
